Metadata-Version: 1.0
Name: nrepl-python-client
Version: 0.0.3
Summary: A Python client for the nREPL Clojure networked-REPL server.
Home-page: https://github.com/cemerick/nrepl-python-client
Author: Chas Emerick
Author-email: chas@cemerick.com
License: MIT License
Keywords: clojure repl nrepl
Platform: any
Classifier: Development Status :: 4 - Beta
Classifier: Environment :: Console
Classifier: Intended Audience :: Developers
Classifier: License :: OSI Approved :: MIT License
Classifier: Natural Language :: English
Classifier: Operating System :: OS Independent
Classifier: Programming Language :: Python
Classifier: Topic :: Software Development :: Interpreters
Classifier: Topic :: Software Development :: Libraries :: Python Modules
Classifier: Topic :: Utilities
